latinsq/__init__.py
latinsq/latinsq.py
latinsq-0.2.3.dist-info/LICENSE
latinsq-0.2.3.dist-info/METADATA
latinsq-0.2.3.dist-info/WHEEL
latinsq-0.2.3.dist-info/top_level.txt
latinsq-0.2.3.dist-info/RECORD
