Metadata-Version: 2.1
Name: latinsq
Version: 0.2.3
Summary: A package for manipulating latin squares
Home-page: https://github.com/ianabc/latinsq
Author: Ian Allison
Author-email: iana@pims.math.ca
License: UNKNOWN
Project-URL: Bug Tracker, https://github.com/ianabc/latinsq/issues
Platform: UNKNOWN
Classifier: Programming Language :: Python :: 3
Classifier: License :: OSI Approved :: MIT License
Classifier: Operating System :: OS Independent
Requires-Python: >=3.6
License-File: LICENSE
Requires-Dist: numpy (>=1.17)
